hestia_earth/aggregation/__init__.py
hestia_earth/aggregation/aggregate_cycles.py
hestia_earth/aggregation/log.py
hestia_earth/aggregation/recalculate_cycles.py
hestia_earth/aggregation/version.py
hestia_earth/aggregation/config/Cycle/processedFood.json
hestia_earth/aggregation/utils/__init__.py
hestia_earth/aggregation/utils/aggregate_country_nodes.py
hestia_earth/aggregation/utils/aggregate_weighted.py
hestia_earth/aggregation/utils/blank_node.py
hestia_earth/aggregation/utils/combine.py
hestia_earth/aggregation/utils/completeness.py
hestia_earth/aggregation/utils/covariance.py
hestia_earth/aggregation/utils/cycle.py
hestia_earth/aggregation/utils/distribution.py
hestia_earth/aggregation/utils/emission.py
hestia_earth/aggregation/utils/group.py
hestia_earth/aggregation/utils/input.py
hestia_earth/aggregation/utils/lookup.py
hestia_earth/aggregation/utils/management.py
hestia_earth/aggregation/utils/measurement.py
hestia_earth/aggregation/utils/practice.py
hestia_earth/aggregation/utils/product.py
hestia_earth/aggregation/utils/property.py
hestia_earth/aggregation/utils/quality_score.py
hestia_earth/aggregation/utils/queries.py
hestia_earth/aggregation/utils/site.py
hestia_earth/aggregation/utils/source.py
hestia_earth/aggregation/utils/term.py
hestia_earth/aggregation/utils/weights.py
hestia_earth_aggregation-0.21.15.dist-info/licenses/LICENSE
hestia_earth_aggregation-0.21.15.dist-info/METADATA
hestia_earth_aggregation-0.21.15.dist-info/WHEEL
hestia_earth_aggregation-0.21.15.dist-info/top_level.txt
hestia_earth_aggregation-0.21.15.dist-info/RECORD
