Metadata-Version: 2.4
Name: hestia_earth_aggregation
Version: 0.21.15
Summary: HESTIA's aggregation engine.
Home-page: https://gitlab.com/hestia-earth/hestia-aggregation-engine
Author: HESTIA Team
Author-email: guillaumeroyer.mail@gmail.com
License: MIT
Classifier: Programming Language :: Python :: 3.12
Requires-Python: >=3.12
License-File: LICENSE
Requires-Dist: hestia-earth-schema<36.0.0,>=35.0.1
Requires-Dist: hestia-earth-utils>=0.16.12
Requires-Dist: hestia-earth-models>=0.75.13
Requires-Dist: requests
Requires-Dist: unidecode
Dynamic: author
Dynamic: author-email
Dynamic: classifier
Dynamic: description
Dynamic: description-content-type
Dynamic: home-page
Dynamic: license
Dynamic: license-file
Dynamic: requires-dist
Dynamic: requires-python
Dynamic: summary
